{"cameraMode":{"drawMode":0,"name":"Shaded","section":"Shading Mode"},"sceneLighting":true,"audioPlay":false,"sceneViewState":{"showFog":true,"showMaterialUpdate":false,"showSkybox":true,"showFlares":true,"showImageEffects":true,"showParticleSystems":true,"showVisualEffectGraphs":true,"m_FxEnabled":true},"in2DMode":false,"pivot":{"x":9.5367431640625e-7,"y":3.049999952316284,"z":-9.5367431640625e-7},"rotation":{"x":-0.5001858472824097,"y":0.4999348223209381,"z":-0.49928146600723269,"w":-0.5007085204124451},"size":10.358694076538086,"orthographic":false}